onepiece_classify/__init__.py
onepiece_classify/data/__init__.py
onepiece_classify/data/setup_data.py
onepiece_classify/infer/__init__.py
onepiece_classify/infer/base.py
onepiece_classify/infer/recognition.py
onepiece_classify/io/__init__.py
onepiece_classify/models/__init__.py
onepiece_classify/models/build_model.py
onepiece_classify/trainer/__init__.py
onepiece_classify/trainer/trainer.py
onepiece_classify/transforms/__init__.py
onepiece_classify/transforms/trans.py
onepiece_classify/utils/__init__.py
onepiece_classify/utils/downloader.py
onepiece_classifier-0.0.3.dist-info/LICENSE
onepiece_classifier-0.0.3.dist-info/METADATA
onepiece_classifier-0.0.3.dist-info/WHEEL
onepiece_classifier-0.0.3.dist-info/top_level.txt
onepiece_classifier-0.0.3.dist-info/RECORD
