Metadata-Version: 2.1
Name: onepiece_classifier
Version: 0.0.3
Summary: package to predict onepiece image character
Home-page: https://github.com/lombokai/onepiece-classifier.git
Author: annur afgoni
Author-email: afgoniannur@gmail.com
Requires-Python: >=3.10
License-File: LICENSE
Requires-Dist: gdown
Requires-Dist: numpy
Requires-Dist: pandas
Requires-Dist: pyarrow
Requires-Dist: torch
Requires-Dist: torchvision
